deepblu_tools/__init__.py
deepblu_tools/deepblu_api.py
deepblu_tools/utils.py
deepblu_tools/bin/__init__.py
deepblu_tools/bin/cli.py
deepblu_tools/models/uddf.py
deepblu_tools/models/deepblu/__init__.py
deepblu_tools/models/deepblu/buddy.py
deepblu_tools/models/deepblu/dive_base.py
deepblu_tools/models/deepblu/dive_gear.py
deepblu_tools/models/deepblu/dive_log.py
deepblu_tools/models/deepblu/dive_profile.py
deepblu_tools/models/deepblu/dive_spot.py
deepblu_tools/models/deepblu/equipment.py
deepblu_tools/models/deepblu/gas_definition.py
deepblu_tools/models/deepblu/log_book.py
deepblu_tools/models/deepblu/medium.py
deepblu_tools/models/deepblu/user.py
deepblu_tools/models/deepblu/way_point.py
deepblu_tools-2.1.4.dist-info/LICENSE
deepblu_tools-2.1.4.dist-info/METADATA
deepblu_tools-2.1.4.dist-info/WHEEL
deepblu_tools-2.1.4.dist-info/entry_points.txt
deepblu_tools-2.1.4.dist-info/top_level.txt
deepblu_tools-2.1.4.dist-info/RECORD
