Metadata-Version: 2.1
Name: deepblu-tools
Version: 2.1.4
Summary: Deepblu Tools
Home-page: https://github.com/bluppfisk/deepblu-tools/
Author: Sander Van de Moortel
Author-email: sander.vandemoortel@gmail.com
License: GPLv3
Project-URL: Documentation, https://github.com/bluppfisk/deepblu-tools/
Platform: any
Classifier: Development Status :: 4 - Beta
Classifier: Programming Language :: Python
License-File: LICENSE
Requires-Dist: requests (~=2.31)
Requires-Dist: xsdata (~=22.7)
Requires-Dist: click (~=8.1.3)
Provides-Extra: develop
Requires-Dist: flake8 ; extra == 'develop'
Requires-Dist: black ; extra == 'develop'
Requires-Dist: virtualenv ; extra == 'develop'
